runescapeapi/__init__.py
runescapeapi/runescapeapi.py
runescapeapi-2.dist-info/METADATA
runescapeapi-2.dist-info/WHEEL
runescapeapi-2.dist-info/top_level.txt
runescapeapi-2.dist-info/RECORD
