Metadata-Version: 2.1
Name: runescapeapi
Version: 2
Summary: grandexchange, highscores, beasts, runemetrics
Home-page: UNKNOWN
Author: raatty
License: MIT
Platform: UNKNOWN
Requires-Python: >=3
